django_logtailer-1.3.0.dist-info/licenses/LICENSE
logtailer/__init__.py
logtailer/admin.py
logtailer/apps.py
logtailer/models.py
logtailer/urls.py
logtailer/views.py
logtailer/locale/en/LC_MESSAGES/django.mo
logtailer/locale/en/LC_MESSAGES/django.po
logtailer/locale/it/LC_MESSAGES/django.mo
logtailer/locale/it/LC_MESSAGES/django.po
logtailer/migrations/0001_initial.py
logtailer/migrations/0002_auto_20210831_0738.py
logtailer/migrations/__init__.py
logtailer/static/logtailer/css/logtailer.css
logtailer/static/logtailer/img/colorbox/border.png
logtailer/static/logtailer/img/colorbox/controls.png
logtailer/static/logtailer/img/colorbox/loading.gif
logtailer/static/logtailer/img/colorbox/loading_background.png
logtailer/static/logtailer/img/colorbox/overlay.png
logtailer/static/logtailer/js/init.js
logtailer/static/logtailer/js/logtailer.js
logtailer/static/logtailer/js/utils.js
logtailer/templates/admin/logtailer/logfile/change_form.html
logtailer/templates/logtailer/log_reader.html
logtailer/templates/logtailer/templatetags/filters.html
logtailer/templatetags/__init__.py
logtailer/templatetags/logtailer_utils.py
django_logtailer-1.3.0.dist-info/METADATA
django_logtailer-1.3.0.dist-info/WHEEL
django_logtailer-1.3.0.dist-info/top_level.txt
django_logtailer-1.3.0.dist-info/RECORD
