Metadata-Version: 2.4
Name: django-logtailer
Version: 1.3.0
Summary: Allows to read log files from disk with a tail like web console on Django admin interface.
Author-email: Mauro <fireantology@gmail.com>
License-Expression: BSD-2-Clause
Project-URL: Homepage, https://github.com/fireantology/django-logtailer
Classifier: Programming Language :: Python :: 3
Classifier: Operating System :: OS Independent
Classifier: Development Status :: 5 - Production/Stable
Classifier: Framework :: Django
Classifier: Intended Audience :: Developers
Classifier: Topic :: Internet :: WWW/HTTP
Classifier: Framework :: Django
Classifier: Framework :: Django :: 4.0
Classifier: Framework :: Django :: 5.0
Requires-Python: >=3.9
License-File: LICENSE
Requires-Dist: Django>=5.0
Dynamic: license-file
